{"end_date": "2026-04-20", "source": "price cache", "contribution": "flat \u20b920k/month", "default_variant": "bb60", "horizons": ["1y", "3y", "5y", "Full"], "variants": [{"key": "bb60", "label": "bb-60"}, {"key": "bb30", "label": "bb-30"}, {"key": "bb60mid", "label": "bb-60 +mid"}], "watchlists": [{"key": "Current", "label": "Current", "is_current": true}, {"key": "backtest_output_archive_20260417", "label": "Prev watchlist", "is_current": false}], "cells": {"Current|bb60|1y": {"xirr": 4.9, "mult": 1.03, "maxdd": -10.0}, "Current|bb60|3y": {"xirr": 7.6, "mult": 1.12, "maxdd": -15.1}, "Current|bb60|5y": {"xirr": 29.2, "mult": 2.06, "maxdd": -32.6}, "Current|bb60|Full": {"xirr": 25.0, "mult": 10.29, "maxdd": -59.4}, "Current|bb30|1y": {"xirr": 9.5, "mult": 1.05, "maxdd": -10.3}, "Current|bb30|3y": {"xirr": 6.9, "mult": 1.11, "maxdd": -13.9}, "Current|bb30|5y": {"xirr": 27.7, "mult": 1.99, "maxdd": -31.8}, "Current|bb30|Full": {"xirr": 25.3, "mult": 10.58, "maxdd": -60.7}, "Current|bb60mid|1y": {"xirr": 16.1, "mult": 1.09, "maxdd": -9.8}, "Current|bb60mid|3y": {"xirr": 9.6, "mult": 1.16, "maxdd": -14.3}, "Current|bb60mid|5y": {"xirr": 28.0, "mult": 2.0, "maxdd": -31.6}, "Current|bb60mid|Full": {"xirr": 24.9, "mult": 10.19, "maxdd": -60.9}, "backtest_output_archive_20260417|bb60|1y": {"xirr": 15.0, "mult": 1.08, "maxdd": -10.6}, "backtest_output_archive_20260417|bb60|3y": {"xirr": 10.1, "mult": 1.17, "maxdd": -16.2}, "backtest_output_archive_20260417|bb60|5y": {"xirr": 29.7, "mult": 2.08, "maxdd": -29.7}, "backtest_output_archive_20260417|bb60|Full": {"xirr": 27.5, "mult": 13.15, "maxdd": -67.7}, "backtest_output_archive_20260417|bb30|1y": {"xirr": 7.9, "mult": 1.04, "maxdd": -10.2}, "backtest_output_archive_20260417|bb30|3y": {"xirr": 9.8, "mult": 1.16, "maxdd": -16.2}, "backtest_output_archive_20260417|bb30|5y": {"xirr": 30.3, "mult": 2.12, "maxdd": -26.5}, "backtest_output_archive_20260417|bb30|Full": {"xirr": 26.5, "mult": 11.87, "maxdd": -63.4}, "backtest_output_archive_20260417|bb60mid|1y": {"xirr": 14.0, "mult": 1.07, "maxdd": -10.3}, "backtest_output_archive_20260417|bb60mid|3y": {"xirr": 8.5, "mult": 1.14, "maxdd": -16.2}, "backtest_output_archive_20260417|bb60mid|5y": {"xirr": 28.5, "mult": 2.02, "maxdd": -30.2}, "backtest_output_archive_20260417|bb60mid|Full": {"xirr": 27.3, "mult": 12.84, "maxdd": -66.7}}}